MANIFEST.in
RELEASE-VERSION
pavement.py
paver-minilib.zip
setup.py
version.py
cairo_helpers/__init__.py
cairo_helpers/font.py
cairo_helpers/surface.py
cairo_helpers.egg-info/PKG-INFO
cairo_helpers.egg-info/SOURCES.txt
cairo_helpers.egg-info/dependency_links.txt
cairo_helpers.egg-info/pbr.json
cairo_helpers.egg-info/top_level.txt