Metadata-Version: 1.0
Name: cairo-helpers
Version: 0.2.post1
Summary: Add description here.
Home-page: https://github.com/wheeler-microfluidics/cairo-helpers
Author: Anonymous
Author-email: you@mail.com
License: GPL
Platform: UNKNOWN
